cgshop2023_pyutils
