Metadata-Version: 2.1
Name: cgshop2023-pyutils
Version: 0.2.4
Summary: Official utilities for the CG:SHOP Challenge 2023.
Home-page: https://github.com/CG-SHOP/pyutils23
Author: TU Braunschweig, IBR, Algorithms Group (Phillip Keldenich and Dominik Krupke)
Author-email: keldenich@ibr.cs.tu-bs.de, krupke@ibr.cs.tu-bs.de
Classifier: Development Status :: 4 - Beta
Classifier: License :: OSI Approved :: MIT License
Classifier: Programming Language :: Python :: 3
Requires-Python: >=3.7
License-File: LICENSE
